pixelsort/__init__.py
pixelsort/__main__.py
pixelsort/argparams.py
pixelsort/constants.py
pixelsort/interval.py
pixelsort/main.py
pixelsort/pixelsort.py
pixelsort/sorter.py
pixelsort/sorting.py
pixelsort/util.py
pixelsort-1.0.1.dist-info/LICENSE
pixelsort-1.0.1.dist-info/METADATA
pixelsort-1.0.1.dist-info/WHEEL
pixelsort-1.0.1.dist-info/top_level.txt
pixelsort-1.0.1.dist-info/RECORD
