Metadata-Version: 2.1
Name: pixelsort
Version: 1.0.1
Summary: An image pixelsorter for Python.
Home-page: https://github.com/satyarth/pixelsort
Author: Bernard Zhao
Author-email: bernardzhao@berkeley.edu
License: UNKNOWN
Platform: UNKNOWN
Classifier: Programming Language :: Python
Classifier: License :: OSI Approved :: MIT License
Classifier: Operating System :: OS Independent
Requires-Dist: Pillow
